sdwss/__init__.py
sdwss/function_params.py
sdwss/hijacker.py
sdwss/plugin_system.py
sdwss/sdwss.py
sdwss/sd_webui/__init__.py
sdwss/sd_webui/api_impl.py
sdwss/sd_webui/gradio_helpers.py
sdwss/sd_webui/img2img_tabs.py
sdwss/sd_webui/prompt_parser.py
sdwss-0.0.1.dist-info/METADATA
sdwss-0.0.1.dist-info/WHEEL
sdwss-0.0.1.dist-info/top_level.txt
sdwss-0.0.1.dist-info/RECORD
