Metadata-Version: 2.1
Name: sdwss
Version: 0.0.1
Summary: Stable Diffusion Library
Author: ljleb
Classifier: Programming Language :: Python :: 3
Classifier: License :: OSI Approved :: MIT License
Classifier: Operating System :: OS Independent
Requires-Python: >=3.8
